{"cameraMode":{"drawMode":0,"name":"Shaded","section":"Shading Mode"},"sceneLighting":true,"audioPlay":false,"sceneViewState":{"m_AlwaysRefresh":false,"showFog":true,"showSkybox":false,"showFlares":true,"showImageEffects":true,"showParticleSystems":true,"showVisualEffectGraphs":true,"m_FxEnabled":true},"in2DMode":false,"pivot":{"x":12.70620346069336,"y":18.42435073852539,"z":0.6508022546768189},"rotation":{"x":-0.2784721553325653,"y":0.6583814024925232,"z":-0.2876381576061249,"w":-0.6373919248580933},"size":15.068880081176758,"orthographic":false}